time_it/__init__.py
time_it/timeit_function.py
time_it_profiler-1.1.1.dist-info/LICENSE
time_it_profiler-1.1.1.dist-info/METADATA
time_it_profiler-1.1.1.dist-info/WHEEL
time_it_profiler-1.1.1.dist-info/top_level.txt
time_it_profiler-1.1.1.dist-info/RECORD
