Metadata-Version: 2.2
Name: time-it-profiler
Version: 1.1.1
Summary: A lightweight Python decorator for measuring execution time and system resource usage.
Home-page: https://github.com/brianvess/time_it.git
Author: Brian Vess
Author-email: brianvess@icloud.com
Classifier: Programming Language :: Python :: 3
Classifier: License :: OSI Approved :: MIT License
Classifier: Operating System :: OS Independent
Requires-Python: >=3.6
License-File: LICENSE
Dynamic: author
Dynamic: author-email
Dynamic: classifier
Dynamic: description
Dynamic: description-content-type
Dynamic: home-page
Dynamic: requires-python
Dynamic: summary
